mathflow/__bridge_stub_helpers.py
mathflow/__init__.py
mathflow/_numerical_bridge_module.py
mathflow/_numerical_bridge_stub.py
mathflow/_repr_bridge_module.py
mathflow/_repr_bridge_stub.py
mathflow/_symbolic_bridge_module.py
mathflow/_symbolic_bridge_stub.py
mathflow/core.py
mathflow/custom_numerical_funcs.py
mathflow/custom_pade_implementation.py
mathflow/parser.py
mathflow-0.1.4.dist-info/licenses/LICENSE
mathflow-0.1.4.dist-info/METADATA
mathflow-0.1.4.dist-info/WHEEL
mathflow-0.1.4.dist-info/top_level.txt
mathflow-0.1.4.dist-info/RECORD
