Metadata-Version: 2.4
Name: mathflow
Version: 0.1.4
Summary: A Pythonic Interface for Symbolic and Numerical Mathematics
Author-email: Isaac Wolford <isaacmwolford@gmail.com>
License-Expression: MIT
Project-URL: Homepage, https://github.com/cybergeek1943/funkit/
Project-URL: Repository, https://github.com/cybergeek1943/funkit/
Requires-Python: >=3.11
License-File: LICENSE
Requires-Dist: sympy
Requires-Dist: scipy
Requires-Dist: tabulate
Dynamic: license-file
